{
  "version": 2,
  "extractor": "papercropper",
  "tables": [
    {
      "url": "assets/tables/aaai-2024-accepted/aaai-2024-29839/table-001.webp",
      "caption": "",
      "page": 0,
      "index": 1,
      "width": 1836,
      "height": 1030,
      "label": "Table"
    },
    {
      "url": "assets/tables/aaai-2024-accepted/aaai-2024-29839/table-002.webp",
      "caption": "",
      "page": 0,
      "index": 2,
      "width": 846,
      "height": 446,
      "label": "Table"
    },
    {
      "url": "assets/tables/aaai-2024-accepted/aaai-2024-29839/table-003.webp",
      "caption": "",
      "page": 0,
      "index": 3,
      "width": 835,
      "height": 394,
      "label": "Table"
    },
    {
      "url": "assets/tables/aaai-2024-accepted/aaai-2024-29839/table-004.webp",
      "caption": "",
      "page": 0,
      "index": 4,
      "width": 865,
      "height": 407,
      "label": "Table"
    }
  ]
}